README.rst
setup.cfg
setup.py
timely.py
timely.egg-info/PKG-INFO
timely.egg-info/SOURCES.txt
timely.egg-info/dependency_links.txt
timely.egg-info/not-zip-safe
timely.egg-info/top_level.txt