Metadata-Version: 1.0
Name: timely
Version: 0.1
Summary: timely :: easy stopwatch interface in Python
Home-page: https://github.com/gyllstromk/python-timely
Author: Karl Gyllstrom
Author-email: karl.gyllstrom+code@gmail.com
License: BSD
Platform: any
